{"type": "FeatureCollection",
"name": "test",
 "features": [{"type": "Feature", "geometry": {"type": "Point", "coordinates": [3.86832, 43.62253]}, "properties": {"id": "3aT", "name": "Composteur collectif Boutonnet", "geo": {"latitude": 43.62253, "longitude": 3.86832}, "sourceKey": "", "address": {"addressLocality": "Montpellier", "addressCountry": "fr"}, "createdAt": "28/02/2020 \u00e0 18:17", "updatedAt": "28/02/2020 \u00e0 18:17", "categories": ["Composteurs"], "categoriesFull": [{"id": 1, "name": "Composteurs", "description": "", "index": 1}], "email": ""}}, {"type": "Feature", "geometry": {"type": "Point", "coordinates": [6.02663, 47.23518]}, "properties": {"id": "TV", "name": "Chalet de compostage", "geo": {"latitude": 47.23518, "longitude": 6.02663}, "sourceKey": "Recycling organic from OSM", "address": {}, "createdAt": "20/02/2020 \u00e0 23:50", "updatedAt": "24/02/2020 \u00e0 23:52", "categories": ["Composteurs"], "categoriesFull": [{"id": 1, "name": "Composteurs", "description": "", "index": 0}], "tags/operator": "SYBERT", "tags/recycling_type": "container", "tags/name": "Chalet de compostage"}}, {"type": "Feature", "geometry": {"type": "Point", "coordinates": [-1.54837, 47.18913]}, "properties": {"id": "TW", "name": "Composteur collectif Lamour \u2013 les Forges", "geo": {"latitude": 47.18913, "longitude": -1.54837}, "sourceKey": "Recycling organic from OSM", "address": {}, "createdAt": "20/02/2020 \u00e0 23:50", "updatedAt": "24/02/2020 \u00e0 23:52", "categories": ["Composteurs"], "categoriesFull": [{"id": 1, "name": "Composteurs", "description": "", "index": 0}], "tags/name": "Composteur collectif Lamour \u2013 les Forges", "Site": "http://roussicompost.servideo.org/"}}, {"type": "Feature", "geometry": {"type": "Point", "coordinates": [3.49897, 43.70059]}, "properties": {"id": "TX", "name": "composteur de montpeyroux", "geo": {"latitude": 43.70059, "longitude": 3.49897}, "sourceKey": "Recycling organic from OSM", "address": {}, "createdAt": "20/02/2020 \u00e0 23:50", "updatedAt": "24/02/2020 \u00e0 23:52", "categories": ["Composteurs"], "categoriesFull": [{"id": 1, "name": "Composteurs", "description": "", "index": 0}], "tags/recycling_type": "container", "tags/recycling:green_waste": "yes", "tags/name": "composteur de montpeyroux"}}]}